pyLoginSystem/__init__.py
pyLoginSystem/prepare_database.py
pyLoginSystem-0.0.2.dist-info/LICENSE
pyLoginSystem-0.0.2.dist-info/METADATA
pyLoginSystem-0.0.2.dist-info/WHEEL
pyLoginSystem-0.0.2.dist-info/top_level.txt
pyLoginSystem-0.0.2.dist-info/RECORD
