Metadata-Version: 2.1
Name: pyLoginSystem
Version: 0.0.2
Summary: A simple python login system using sql alchemy
Home-page: https://www.github.com/uklewis124/LoginSystem
Author: Lewis Davies
Author-email: lewisastondavies1@gmail.com
Classifier: Programming Language :: Python :: 3
Classifier: License :: OSI Approved :: MIT License
Classifier: Operating System :: OS Independent
Requires-Python: >=3.6
License-File: LICENSE
